pyramid_xslt
