Metadata-Version: 1.1
Name: pyramid-xslt
Version: 0.1
Summary: Xslt renderer for pyramid
Home-page: https://github.com/cyplp/pyramid_xslt
Author: Cyprien Le Pannérer
Author-email: cyplp@free.fr
License: MIT
Keywords: pyramid xslt renderer
Platform: UNKNOWN
Classifier: Framework :: Pyramid
Classifier: License :: OSI Approved :: MIT License
Classifier: Topic :: Text Processing :: Markup :: XML
